[
  {
    "brandCode": "brand-151",
    "brandName": "现代",
    "buttonDesc": "询底价",
    "carId": "n1sTa67R8K",
    "carSourceExt": "xdfc",
    "cityName": "",
    "dealPrice": "75800",
    "detectionFinished": false,
    "emissionStandard": "国六",
    "firstLicensePlateDate": "2025-09-01 00:00:00",
    "firstLicensePlateDateStr": "2025年09月",
    "guidePrice": 112800,
    "hasDownPayment": false,
    "hasVideo": false,
    "mileage": 0,
    "mileageStr": "0.00万公里",
    "miniAppFavorite": false,
    "modelName": "2023款 1.5L CVT GLX精英版",
    "needAsh": true,
    "newPrice": 112800,
    "orgId": "FBKIzEGLG1",
    "salePrice": 83800,
    "salePriceStr": "7.58",
    "seriesCode": "series-212",
    "seriesImg": "https://img.souche.com/88DE277B-F17D-4045-A3FF-6D9615E79D56.png",
    "seriesName": "现代伊兰特",
    "shopCode": "01323344",
    "status": "5",
    "storageAge": "库龄16天",
    "thirdPartyDetectionFinished": false,
    "type": "car",
    "vinNumber": "LBECNAFD3SZ523233"
  },
  {
    "brandCode": "brand-151",
    "brandName": "现代",
    "buttonDesc": "询底价",
    "carId": "jTcJP7P4CG",
    "carSourceExt": "xdfc",
    "cityName": "",
    "detectionFinished": false,
    "emissionStandard": "国六",
    "firstLicensePlateDate": "2025-09-01 00:00:00",
    "firstLicensePlateDateStr": "2025年09月",
    "guidePrice": 112800,
    "hasDownPayment": false,
    "hasVideo": false,
    "mileage": 0,
    "mileageStr": "0.00万公里",
    "miniAppFavorite": false,
    "modelName": "2023款 1.5L CVT GLX精英版",
    "needAsh": true,
    "newPrice": 112800,
    "orgId": "FBKIzEGLG1",
    "salePrice": 83800,
    "salePriceStr": "7.58",
    "seriesCode": "series-212",
    "seriesImg": "https://img.souche.com/B034EADC-9566-45E7-8D8B-5D39627BB348.png",
    "seriesName": "现代伊兰特",
    "shopCode": "01323344",
    "status": "4",
    "storageAge": "库龄15天",
    "thirdPartyDetectionFinished": false,
    "type": "car",
    "vinNumber": "LBECNAFD0SZ524159"
  },
  {
    "brandCode": "brand-49",
    "brandName": "丰田",
    "buttonDesc": "询底价",
    "carId": "nmuMaYNH5D",
    "carSourceExt": "xdfc",
    "cityName": "",
    "detectionFinished": false,
    "emissionStandard": "国六",
    "firstLicensePlateDate": "2022-04-08 00:00:00",
    "firstLicensePlateDateStr": "2022年04月",
    "guidePrice": 150800,
    "hasDownPayment": false,
    "hasVideo": false,
    "mileage": 59000,
    "mileageStr": "5.90万公里",
    "miniAppFavorite": false,
    "modelName": "2021款 2.0L 豪华版",
    "needAsh": true,
    "newPrice": 150800,
    "orgId": "FBKIzEGLG1",
    "salePrice": 83800,
    "salePriceStr": "7.58",
    "seriesCode": "series-52097",
    "seriesImg": "https://img.souche.com/B4203813-7304-496F-9530-D95EAC1EA121.png",
    "seriesName": "丰田亚洲狮",
    "shopCode": "01323344",
    "status": "5",
    "storageAge": "库龄16天",
    "thirdPartyDetectionFinished": false,
    "type": "car",
    "vinNumber": "LFMAC1DM7N0040658"
  },
  {
    "brandCode": "brand-151",
    "brandName": "现代",
    "buttonDesc": "询底价",
    "carId": "kCg7N5eKKp",
    "carSourceExt": "xdfc",
    "cityName": "",
    "detectionFinished": false,
    "emissionStandard": "国六",
    "firstLicensePlateDate": "2025-09-01 00:00:00",
    "firstLicensePlateDateStr": "2025年09月",
    "guidePrice": 112800,
    "hasDownPayment": false,
    "hasVideo": false,
    "mileage": 0,
    "mileageStr": "0.00万公里",
    "miniAppFavorite": false,
    "modelName": "2023款 1.5L CVT GLX精英版",
    "needAsh": true,
    "newPrice": 112800,
    "orgId": "FBKIzEGLG1",
    "salePrice": 83800,
    "salePriceStr": "7.58",
    "seriesCode": "series-212",
    "seriesImg": "https://img.souche.com/70592A1F-015C-436D-9209-2703B809FB28.png",
    "seriesName": "现代伊兰特",
    "shopCode": "01323344",
    "status": "4",
    "storageAge": "库龄13天",
    "thirdPartyDetectionFinished": false,
    "type": "car",
    "vinNumber": "LBECNAFD7SZ515880"
  },
  {
    "brandCode": "brand-151",
    "brandName": "现代",
    "buttonDesc": "询底价",
    "carId": "oYQjT5OXjW",
    "carSourceExt": "xdfc",
    "cityName": "",
    "detectionFinished": false,
    "emissionStandard": "国六",
    "firstLicensePlateDate": "2025-09-01 00:00:00",
    "firstLicensePlateDateStr": "2025年09月",
    "guidePrice": 112800,
    "hasDownPayment": false,
    "hasVideo": false,
    "mileage": 0,
    "mileageStr": "0.00万公里",
    "miniAppFavorite": false,
    "modelName": "2023款 1.5L CVT GLX精英版",
    "needAsh": true,
    "newPrice": 112800,
    "orgId": "FBKIzEGLG1",
    "salePrice": 83800,
    "salePriceStr": "7.58",
    "seriesCode": "series-212",
    "seriesImg": "https://img.souche.com/AE97CC50-073F-4274-98A1-E0F3DB049912.png",
    "seriesName": "现代伊兰特",
    "shopCode": "01323344",
    "status": "4",
    "storageAge": "库龄13天",
    "thirdPartyDetectionFinished": false,
    "type": "car",
    "vinNumber": "LBECNAFD3SZ514631"
  },
  {
    "brandCode": "brand-151",
    "brandName": "现代",
    "buttonDesc": "询底价",
    "carId": "kcusqzzRa6",
    "carSourceExt": "xdfc",
    "cityName": "",
    "detectionFinished": false,
    "emissionStandard": "国六",
    "firstLicensePlateDate": "2025-09-01 00:00:00",
    "firstLicensePlateDateStr": "2025年09月",
    "guidePrice": 112800,
    "hasDownPayment": false,
    "hasVideo": false,
    "mileage": 0,
    "mileageStr": "0.00万公里",
    "miniAppFavorite": false,
    "modelName": "2023款 1.5L CVT GLX精英版",
    "needAsh": true,
    "newPrice": 112800,
    "orgId": "FBKIzEGLG1",
    "salePrice": 83800,
    "salePriceStr": "7.58",
    "seriesCode": "series-212",
    "seriesImg": "https://img.souche.com/1B0CE9B6-B8F1-445B-81FD-B51BBC3ED473.png",
    "seriesName": "现代伊兰特",
    "shopCode": "01323344",
    "status": "4",
    "storageAge": "库龄15天",
    "thirdPartyDetectionFinished": false,
    "type": "car",
    "vinNumber": "LBECNAFD2SZ522977"
  },
  {
    "brandCode": "brand-74",
    "brandName": "Jeep",
    "buttonDesc": "询底价",
    "carId": "iUuYSVJ3yY",
    "carSourceExt": "xdfc",
    "cityName": "",
    "detectionFinished": false,
    "emissionStandard": "国六",
    "firstLicensePlateDate": "2020-11-16 00:00:00",
    "firstLicensePlateDateStr": "2020年11月",
    "guidePrice": 179800,
    "hasDownPayment": false,
    "hasVideo": false,
    "mileage": 85000,
    "mileageStr": "8.50万公里",
    "miniAppFavorite": false,
    "modelName": "2020款 2.0L 两驱经典运动版",
    "needAsh": true,
    "newPrice": 179800,
    "orgId": "FBKIzEGLG1",
    "salePrice": 83800,
    "salePriceStr": "7.58",
    "seriesCode": "series-50084",
    "seriesImg": "https://img.souche.com/AB9BD06A-7D57-499F-84B3-788CE0F5B917.png",
    "seriesName": "Jeep自由光",
    "shopCode": "01323344",
    "status": "5",
    "storageAge": "库龄22天",
    "thirdPartyDetectionFinished": false,
    "type": "car",
    "vinNumber": "LWVCBE760LA244902"
  },
  {
    "brandCode": "brand-151",
    "brandName": "现代",
    "buttonDesc": "询底价",
    "carId": "lxKw71VoXK",
    "carSourceExt": "xdfc",
    "cityName": "",
    "detectionFinished": false,
    "emissionStandard": "国六",
    "firstLicensePlateDate": "2025-09-01 00:00:00",
    "firstLicensePlateDateStr": "2025年09月",
    "guidePrice": 112800,
    "hasDownPayment": false,
    "hasVideo": false,
    "mileage": 0,
    "mileageStr": "0.00万公里",
    "miniAppFavorite": false,
    "modelName": "2023款 1.5L CVT GLX精英版",
    "needAsh": true,
    "newPrice": 112800,
    "orgId": "FBKIzEGLG1",
    "salePrice": 83800,
    "salePriceStr": "7.58",
    "seriesCode": "series-212",
    "seriesImg": "https://img.souche.com/FF673F0A-D96C-4758-B767-0DD156ECCBCD.png",
    "seriesName": "现代伊兰特",
    "shopCode": "01323344",
    "status": "4",
    "storageAge": "库龄10天",
    "thirdPartyDetectionFinished": false,
    "type": "car",
    "vinNumber": "LBECNAFD4SZ522656"
  },
  {
    "brandCode": "brand-29",
    "brandName": "标致",
    "buttonDesc": "询底价",
    "carId": "inuCJI8ueB",
    "carSourceExt": "xdfc",
    "cityName": "",
    "detectionFinished": false,
    "emissionStandard": "国六",
    "firstLicensePlateDateStr": "",
    "guidePrice": 109700,
    "hasDownPayment": false,
    "hasVideo": false,
    "mileage": 0,
    "mileageStr": "0.00万公里",
    "miniAppFavorite": false,
    "modelName": "2024款 360THP 龘龘款 罗曼尼版",
    "needAsh": true,
    "newPrice": 109700,
    "orgId": "FBKIzEGLG1",
    "salePrice": 83800,
    "salePriceStr": "7.58",
    "seriesCode": "series-1900",
    "seriesImg": "https://img.souche.com/ECBE2E35-569A-4C05-B84C-A5A0FA607485.png",
    "seriesName": "标致408",
    "shopCode": "01323344",
    "status": "5",
    "storageAge": "库龄14天",
    "thirdPartyDetectionFinished": false,
    "type": "car",
    "vinNumber": "LDC973B45S3005793"
  },
  {
    "brandCode": "brand-151",
    "brandName": "现代",
    "buttonDesc": "询底价",
    "carId": "k1cVzBYI72",
    "carSourceExt": "xdfc",
    "cityName": "",
    "detectionFinished": false,
    "emissionStandard": "国六",
    "firstLicensePlateDate": "2025-09-01 00:00:00",
    "firstLicensePlateDateStr": "2025年09月",
    "guidePrice": 112800,
    "hasDownPayment": false,
    "hasVideo": false,
    "mileage": 0,
    "mileageStr": "0.00万公里",
    "miniAppFavorite": false,
    "modelName": "2023款 1.5L CVT GLX精英版",
    "needAsh": true,
    "newPrice": 112800,
    "orgId": "FBKIzEGLG1",
    "salePrice": 83800,
    "salePriceStr": "7.58",
    "seriesCode": "series-212",
    "seriesImg": "https://img.souche.com/2EED87CB-12F6-4C52-B76A-1BD4CCD05ECF.png",
    "seriesName": "现代伊兰特",
    "shopCode": "01323344",
    "status": "4",
    "storageAge": "库龄13天",
    "thirdPartyDetectionFinished": false,
    "type": "car",
    "vinNumber": "LBECNAFD8SZ515032"
  }
]