[
  {
    "brandCode": "brand-121",
    "brandName": "日产",
    "buttonDesc": "询底价",
    "carId": "0e6l5APPYd",
    "carSourceExt": "xdfc",
    "cityName": "",
    "detectionFinished": false,
    "emissionStandard": "国六",
    "firstLicensePlateDateStr": "",
    "guidePrice": 125900,
    "hasDownPayment": false,
    "hasVideo": false,
    "mileage": 0,
    "mileageStr": "0.00万公里",
    "miniAppFavorite": false,
    "modelName": "2025款 荣誉 2.0L CVT XV真心版",
    "needAsh": true,
    "newPrice": 125900,
    "orgId": "FBKIzEGLG1",
    "salePrice": 101800,
    "salePriceStr": "9.38",
    "seriesCode": "series-133",
    "seriesImg": "https://img.souche.com/01AA5F3E-C9EB-4BC3-A99A-3A9C9F7CDC8C.png",
    "seriesName": "日产逍客",
    "shopCode": "01323344",
    "status": "4",
    "storageAge": "库龄20天",
    "thirdPartyDetectionFinished": false,
    "type": "car",
    "vinNumber": "LGBL4AE06SD056724"
  },
  {
    "brandCode": "brand-1112",
    "brandName": "吉利银河",
    "buttonDesc": "询底价",
    "carId": "0agrfjWFT7",
    "carSourceExt": "xdfc",
    "cityName": "",
    "detectionFinished": false,
    "emissionStandard": "国六",
    "firstLicensePlateDate": "2025-09-01 00:00:00",
    "firstLicensePlateDateStr": "2025年09月",
    "guidePrice": 116800,
    "hasDownPayment": false,
    "hasVideo": false,
    "mileage": 0,
    "mileageStr": "0.00万公里",
    "miniAppFavorite": false,
    "modelName": "2025款 EM-I 120KM启航+版",
    "needAsh": true,
    "newPrice": 116800,
    "orgId": "FBKIzEGLG1",
    "salePrice": 101800,
    "salePriceStr": "9.38",
    "seriesCode": "series-53605",
    "seriesImg": "https://img.souche.com/ACBA8154-0DAD-4EB2-AA2D-D60B20B43DD6.png",
    "seriesName": "吉利银河银河星舰7",
    "shopCode": "01323344",
    "status": "4",
    "storageAge": "库龄10天",
    "thirdPartyDetectionFinished": false,
    "type": "car",
    "vinNumber": "LB378JNZOSH067244"
  },
  {
    "brandCode": "brand-1112",
    "brandName": "吉利银河",
    "buttonDesc": "询底价",
    "carId": "1q6tzG4fS7",
    "carSourceExt": "xdfc",
    "cityName": "",
    "detectionFinished": false,
    "emissionStandard": "国六",
    "firstLicensePlateDate": "2025-09-01 00:00:00",
    "firstLicensePlateDateStr": "2025年09月",
    "guidePrice": 116800,
    "hasDownPayment": false,
    "hasVideo": false,
    "mileage": 0,
    "mileageStr": "0.00万公里",
    "miniAppFavorite": false,
    "modelName": "2025款 EM-I 120KM启航+版",
    "needAsh": true,
    "newPrice": 116800,
    "orgId": "FBKIzEGLG1",
    "salePrice": 101800,
    "salePriceStr": "9.38",
    "seriesCode": "series-53605",
    "seriesImg": "https://img.souche.com/F9A90A40-E20F-4865-B2D1-9E8053AD6D4F.png",
    "seriesName": "吉利银河银河星舰7",
    "shopCode": "01323344",
    "status": "4",
    "storageAge": "库龄10天",
    "thirdPartyDetectionFinished": false,
    "type": "car",
    "vinNumber": "LB378JNZ6SH060525"
  },
  {
    "brandCode": "brand-20",
    "brandName": "宝马",
    "buttonDesc": "询底价",
    "carId": "pS8sggWWtM",
    "carSourceExt": "xdfc",
    "cityName": "",
    "detectionFinished": false,
    "emissionStandard": "国六",
    "firstLicensePlateDate": "2019-10-08 00:00:00",
    "firstLicensePlateDateStr": "2019年10月",
    "guidePrice": 276800,
    "hasDownPayment": false,
    "hasVideo": false,
    "mileage": 42000,
    "mileageStr": "4.20万公里",
    "miniAppFavorite": false,
    "modelName": "2019款 sDrive18Li 时尚型",
    "needAsh": true,
    "newPrice": 276800,
    "orgId": "FBKIzEGLG1",
    "salePrice": 103800,
    "salePriceStr": "9.58",
    "seriesCode": "series-2487",
    "seriesImg": "https://img.souche.com/0127AE33-D7E6-4BE9-BA5B-071DE4E9CE83.png",
    "seriesName": "宝马X1",
    "shopCode": "01323344",
    "status": "5",
    "storageAge": "库龄27天",
    "thirdPartyDetectionFinished": false,
    "type": "car",
    "vinNumber": "LBVHZ1106KMP81435"
  },
  {
    "brandCode": "brand-27",
    "brandName": "本田",
    "buttonDesc": "询底价",
    "carId": "f3aY7uPfPL",
    "carSourceExt": "xdfc",
    "cityName": "",
    "detectionFinished": false,
    "emissionStandard": "国五",
    "firstLicensePlateDate": "2018-02-02 00:00:00",
    "firstLicensePlateDateStr": "2018年02月",
    "guidePrice": 203800,
    "hasDownPayment": false,
    "hasVideo": false,
    "mileage": 89200,
    "mileageStr": "8.92万公里",
    "miniAppFavorite": false,
    "modelName": "2017款 240TURBO CVT两驱风尚版",
    "needAsh": true,
    "newPrice": 203800,
    "orgId": "FBKIzEGLG1",
    "salePrice": 103800,
    "salePriceStr": "9.58",
    "seriesCode": "series-226",
    "seriesImg": "https://img.souche.com/72AEAE9C-330B-41C1-B810-A21D76FA22DD.png",
    "seriesName": "本田CR-V",
    "shopCode": "01323344",
    "status": "5",
    "storageAge": "库龄13天",
    "thirdPartyDetectionFinished": false,
    "type": "car",
    "vinNumber": "LVHRW1857J5094449"
  },
  {
    "brandCode": "brand-121",
    "brandName": "日产",
    "buttonDesc": "询底价",
    "carId": "unumJTFXKw",
    "carSourceExt": "xdfc",
    "cityName": "",
    "detectionFinished": false,
    "emissionStandard": "国六",
    "firstLicensePlateDate": "2021-05-09 00:00:00",
    "firstLicensePlateDateStr": "2021年05月",
    "guidePrice": 199300,
    "hasDownPayment": false,
    "hasVideo": false,
    "mileage": 54000,
    "mileageStr": "5.40万公里",
    "miniAppFavorite": false,
    "modelName": "2019款 2.0L CVT智联舒适版 2WD 国Ⅵ",
    "needAsh": true,
    "newPrice": 199300,
    "orgId": "FBKIzEGLG1",
    "salePrice": 103800,
    "salePriceStr": "9.58",
    "seriesCode": "series-594",
    "seriesImg": "https://img.souche.com/F6B676B0-7993-4D5D-B648-982CE372DF3C.png",
    "seriesName": "日产奇骏",
    "shopCode": "01323344",
    "status": "5",
    "storageAge": "库龄34天",
    "thirdPartyDetectionFinished": false,
    "type": "car",
    "vinNumber": "LGBM4AE46MS470186"
  },
  {
    "brandCode": "brand-165",
    "brandName": "长城",
    "buttonDesc": "询底价",
    "carId": "lxcjQoVQ4G",
    "carSourceExt": "xdfc",
    "cityName": "",
    "detectionFinished": false,
    "emissionStandard": "国六",
    "firstLicensePlateDate": "2023-05-05 00:00:00",
    "firstLicensePlateDateStr": "2023年05月",
    "guidePrice": 119800,
    "hasDownPayment": false,
    "hasVideo": false,
    "mileage": 33000,
    "mileageStr": "3.30万公里",
    "miniAppFavorite": false,
    "modelName": "2023款 2.0T商用版自动柴油两驱精英型长箱GW4D20M",
    "needAsh": true,
    "newPrice": 119800,
    "orgId": "FBKIzEGLG1",
    "salePrice": 103800,
    "salePriceStr": "9.58",
    "seriesCode": "series-51399",
    "seriesImg": "https://img.souche.com/44FE9B75-8844-4170-AA11-1C832A72C37F.png",
    "seriesName": "长城炮",
    "shopCode": "01323344",
    "status": "5",
    "storageAge": "库龄52天",
    "thirdPartyDetectionFinished": false,
    "type": "car",
    "vinNumber": "LGWCBF1A7PJ051573"
  }
]