[
  {
    "brandCode": "brand-41",
    "brandName": "大众",
    "buttonDesc": "询底价",
    "carId": "isAha38406",
    "carSourceExt": "xdfc",
    "cityName": "",
    "detectionFinished": false,
    "emissionStandard": "国六",
    "firstLicensePlateDate": "2023-07-01 00:00:00",
    "firstLicensePlateDateStr": "2023年07月",
    "guidePrice": 120900,
    "hasDownPayment": false,
    "hasVideo": false,
    "mileage": 83000,
    "mileageStr": "8.30万公里",
    "miniAppFavorite": false,
    "modelName": "2023款 1.5L 自动得逸版",
    "needAsh": true,
    "newPrice": 120900,
    "orgId": "FBKIzEGLG1",
    "salePrice": 61800,
    "salePriceStr": "5.38",
    "seriesCode": "series-340",
    "seriesImg": "https://img.souche.com/D0DDAE36-333B-400F-A7AC-84A3420CB184.png",
    "seriesName": "大众朗逸",
    "shopCode": "01323344",
    "status": "4",
    "storageAge": "库龄16天",
    "thirdPartyDetectionFinished": false,
    "type": "car",
    "vinNumber": "LSVNP60C7PN050273"
  },
  {
    "brandCode": "brand-41",
    "brandName": "大众",
    "buttonDesc": "询底价",
    "carId": "nresaRcGml",
    "carSourceExt": "xdfc",
    "cityName": "",
    "detectionFinished": false,
    "emissionStandard": "国六",
    "firstLicensePlateDate": "2023-07-01 00:00:00",
    "firstLicensePlateDateStr": "2023年07月",
    "guidePrice": 120900,
    "hasDownPayment": false,
    "hasVideo": false,
    "mileage": 66100,
    "mileageStr": "6.61万公里",
    "miniAppFavorite": false,
    "modelName": "2023款 1.5L 自动得逸版",
    "needAsh": true,
    "newPrice": 120900,
    "orgId": "FBKIzEGLG1",
    "salePrice": 61800,
    "salePriceStr": "5.38",
    "seriesCode": "series-340",
    "seriesImg": "https://img.souche.com/89540DB4-1535-4CF6-92A8-52C4DD2AC3C1.png",
    "seriesName": "大众朗逸",
    "shopCode": "01323344",
    "status": "4",
    "storageAge": "库龄16天",
    "thirdPartyDetectionFinished": false,
    "type": "car",
    "vinNumber": "LSVNP60C5PN050031"
  },
  {
    "brandCode": "brand-122",
    "brandName": "荣威",
    "buttonDesc": "询底价",
    "carId": "kjaQHsoqsw",
    "carSourceExt": "xdfc",
    "cityName": "",
    "detectionFinished": false,
    "emissionStandard": "国六",
    "firstLicensePlateDateStr": "",
    "guidePrice": 80900,
    "hasDownPayment": false,
    "hasVideo": false,
    "mileage": 0,
    "mileageStr": "0.00万公里",
    "miniAppFavorite": false,
    "modelName": "2023款 1.5L CVT豪华版",
    "needAsh": true,
    "newPrice": 80900,
    "orgId": "FBKIzEGLG1",
    "salePrice": 61800,
    "salePriceStr": "5.38",
    "seriesCode": "series-51146",
    "seriesImg": "https://img.souche.com/5A66021C-EFDA-41E9-9B25-5D790622239E.png",
    "seriesName": "荣威i5",
    "shopCode": "01323344",
    "status": "4",
    "storageAge": "库龄11天",
    "thirdPartyDetectionFinished": false,
    "type": "car",
    "vinNumber": "LSJA36U36SZ699389"
  },
  {
    "brandCode": "brand-41",
    "brandName": "大众",
    "buttonDesc": "询底价",
    "carId": "lRuEIGEtOy",
    "carSourceExt": "xdfc",
    "cityName": "",
    "detectionFinished": false,
    "emissionStandard": "国六",
    "firstLicensePlateDate": "2023-07-01 00:00:00",
    "firstLicensePlateDateStr": "2023年07月",
    "guidePrice": 120900,
    "hasDownPayment": false,
    "hasVideo": false,
    "mileage": 91500,
    "mileageStr": "9.15万公里",
    "miniAppFavorite": false,
    "modelName": "2023款 1.5L 自动得逸版",
    "needAsh": true,
    "newPrice": 120900,
    "orgId": "FBKIzEGLG1",
    "salePrice": 61800,
    "salePriceStr": "5.38",
    "seriesCode": "series-340",
    "seriesImg": "https://img.souche.com/7ED62B8A-329F-46BE-8B9A-B6EDA6212388.png",
    "seriesName": "大众朗逸",
    "shopCode": "01323344",
    "status": "4",
    "storageAge": "库龄16天",
    "thirdPartyDetectionFinished": false,
    "type": "car",
    "vinNumber": "LSVNP60C7PN045879"
  },
  {
    "brandCode": "brand-41",
    "brandName": "大众",
    "buttonDesc": "询底价",
    "carId": "iusvQf5CnV",
    "carSourceExt": "xdfc",
    "cityName": "",
    "detectionFinished": false,
    "emissionStandard": "国六",
    "firstLicensePlateDate": "2023-07-01 00:00:00",
    "firstLicensePlateDateStr": "2023年07月",
    "guidePrice": 120900,
    "hasDownPayment": false,
    "hasVideo": false,
    "mileage": 85000,
    "mileageStr": "8.50万公里",
    "miniAppFavorite": false,
    "modelName": "2023款 1.5L 自动得逸版",
    "needAsh": true,
    "newPrice": 120900,
    "orgId": "FBKIzEGLG1",
    "salePrice": 61800,
    "salePriceStr": "5.38",
    "seriesCode": "series-340",
    "seriesImg": "https://img.souche.com/DE10EE83-5CE8-4F1C-B067-D07FA857D8D7.png",
    "seriesName": "大众朗逸",
    "shopCode": "01323344",
    "status": "4",
    "storageAge": "库龄16天",
    "thirdPartyDetectionFinished": false,
    "type": "car",
    "vinNumber": "LSVNP60C0PN049479"
  },
  {
    "brandCode": "brand-41",
    "brandName": "大众",
    "buttonDesc": "询底价",
    "carId": "nCqYTvaGhs",
    "carSourceExt": "xdfc",
    "cityName": "",
    "detectionFinished": false,
    "emissionStandard": "国六",
    "firstLicensePlateDate": "2023-06-01 00:00:00",
    "firstLicensePlateDateStr": "2023年06月",
    "guidePrice": 120900,
    "hasDownPayment": false,
    "hasVideo": false,
    "mileage": 87000,
    "mileageStr": "8.70万公里",
    "miniAppFavorite": false,
    "modelName": "2023款 1.5L 自动得逸版",
    "needAsh": true,
    "newPrice": 120900,
    "orgId": "FBKIzEGLG1",
    "salePrice": 61800,
    "salePriceStr": "5.38",
    "seriesCode": "series-340",
    "seriesImg": "https://img.souche.com/41D54F1E-2490-43A0-964F-3A64FDB22EFE.png",
    "seriesName": "大众朗逸",
    "shopCode": "01323344",
    "status": "4",
    "storageAge": "库龄16天",
    "thirdPartyDetectionFinished": false,
    "type": "car",
    "vinNumber": "LSVNF60C1NN097458"
  },
  {
    "brandCode": "brand-41",
    "brandName": "大众",
    "buttonDesc": "询底价",
    "carId": "rcO2EsZuSl",
    "carSourceExt": "xdfc",
    "cityName": "",
    "detectionFinished": false,
    "emissionStandard": "国六",
    "firstLicensePlateDate": "2023-07-01 00:00:00",
    "firstLicensePlateDateStr": "2023年07月",
    "guidePrice": 143900,
    "hasDownPayment": false,
    "hasVideo": false,
    "mileage": 117000,
    "mileageStr": "11.70万公里",
    "miniAppFavorite": false,
    "modelName": "2023款 200TSI DSG 悦智联版",
    "needAsh": true,
    "newPrice": 143900,
    "orgId": "FBKIzEGLG1",
    "salePrice": 61800,
    "salePriceStr": "5.38",
    "seriesCode": "series-51666",
    "seriesImg": "https://img.souche.com/35BA6123-06AA-4779-A90D-199FCB0550FD.png",
    "seriesName": "大众探影",
    "shopCode": "01323344",
    "status": "4",
    "storageAge": "库龄51天",
    "thirdPartyDetectionFinished": false,
    "type": "car",
    "vinNumber": "LFV1B2C17P3708696"
  },
  {
    "brandCode": "brand-41",
    "brandName": "大众",
    "buttonDesc": "询底价",
    "carId": "rucJzThIjV",
    "carSourceExt": "xdfc",
    "cityName": "",
    "detectionFinished": false,
    "emissionStandard": "国六",
    "firstLicensePlateDate": "2023-07-01 00:00:00",
    "firstLicensePlateDateStr": "2023年07月",
    "guidePrice": 120900,
    "hasDownPayment": false,
    "hasVideo": false,
    "mileage": 71000,
    "mileageStr": "7.10万公里",
    "miniAppFavorite": false,
    "modelName": "2023款 1.5L 自动得逸版",
    "needAsh": true,
    "newPrice": 120900,
    "orgId": "FBKIzEGLG1",
    "salePrice": 61800,
    "salePriceStr": "5.38",
    "seriesCode": "series-340",
    "seriesImg": "https://img.souche.com/FAF47181-C2ED-4955-99B1-F394A1BC537F.png",
    "seriesName": "大众朗逸",
    "shopCode": "01323344",
    "status": "4",
    "storageAge": "库龄16天",
    "thirdPartyDetectionFinished": false,
    "type": "car",
    "vinNumber": "LSVNP60C4PN050148"
  }
]